{
    "billing.bundle.js": "/assets/frappe/dist/js/billing.bundle.JNJVHQVG.js",
    "bootstrap-4-web.bundle.js": "/assets/frappe/dist/js/bootstrap-4-web.bundle.AZ67VXZX.js",
    "controls.bundle.js": "/assets/frappe/dist/js/controls.bundle.AO6DM6SH.js",
    "data_import_tools.bundle.js": "/assets/frappe/dist/js/data_import_tools.bundle.OT4HV4C6.js",
    "desk.bundle.js": "/assets/frappe/dist/js/desk.bundle.Z44IL3CY.js",
    "dialog.bundle.js": "/assets/frappe/dist/js/dialog.bundle.MNMQVOPL.js",
    "form.bundle.js": "/assets/frappe/dist/js/form.bundle.ZW4BUDJ5.js",
    "frappe-web.bundle.js": "/assets/frappe/dist/js/frappe-web.bundle.HIC7R6YZ.js",
    "libs.bundle.js": "/assets/frappe/dist/js/libs.bundle.LLRFRX7M.js",
    "list.bundle.js": "/assets/frappe/dist/js/list.bundle.UV7WIWCQ.js",
    "logtypes.bundle.js": "/assets/frappe/dist/js/logtypes.bundle.MJKW7EK3.js",
    "onboarding_tours.bundle.js": "/assets/frappe/dist/js/onboarding_tours.bundle.P7QYMXLW.js",
    "report.bundle.js": "/assets/frappe/dist/js/report.bundle.NLNF6QB4.js",
    "sentry.bundle.js": "/assets/frappe/dist/js/sentry.bundle.SI3DB3BY.js",
    "telemetry.bundle.js": "/assets/frappe/dist/js/telemetry.bundle.ZJBT5ETW.js",
    "user_profile_controller.bundle.js": "/assets/frappe/dist/js/user_profile_controller.bundle.5FTRDXWL.js",
    "video_player.bundle.js": "/assets/frappe/dist/js/video_player.bundle.IOEIXC2G.js",
    "web_form.bundle.js": "/assets/frappe/dist/js/web_form.bundle.QSGJUOFE.js",
    "form_builder.bundle.js": "/assets/frappe/dist/js/form_builder.bundle.M3E2TZLU.js",
    "print_format_builder.bundle.js": "/assets/frappe/dist/js/print_format_builder.bundle.FLEQA5TW.js",
    "workflow_builder.bundle.js": "/assets/frappe/dist/js/workflow_builder.bundle.7Q4THPTQ.js",
    "build_events.bundle.js": "/assets/frappe/dist/js/build_events.bundle.M4PBRQZV.js",
    "file_uploader.bundle.js": "/assets/frappe/dist/js/file_uploader.bundle.AKQBZSGD.js",
    "kanban_board.bundle.js": "/assets/frappe/dist/js/kanban_board.bundle.2KHIS3VS.js",
    "desk.bundle.css": "/assets/frappe/dist/css/desk.bundle.ZEEN22LR.css",
    "email.bundle.css": "/assets/frappe/dist/css/email.bundle.6TSDWGPM.css",
    "login.bundle.css": "/assets/frappe/dist/css/login.bundle.Y4NNUWHH.css",
    "print.bundle.css": "/assets/frappe/dist/css/print.bundle.M2CKG4HJ.css",
    "print_format.bundle.css": "/assets/frappe/dist/css/print_format.bundle.5O4F5L2F.css",
    "report.bundle.css": "/assets/frappe/dist/css/report.bundle.JK374KAG.css",
    "web_form.bundle.css": "/assets/frappe/dist/css/web_form.bundle.B7KWSUXQ.css",
    "website.bundle.css": "/assets/frappe/dist/css/website.bundle.F5X2MUTJ.css",
    "healthcare.bundle.js": "/assets/healthcare/dist/js/healthcare.bundle.PVD4GEY3.js",
    "bank-reconciliation-tool.bundle.js": "/assets/erpnext/dist/js/bank-reconciliation-tool.bundle.G7MHMAFO.js",
    "erpnext-web.bundle.js": "/assets/erpnext/dist/js/erpnext-web.bundle.253I7LT4.js",
    "erpnext.bundle.js": "/assets/erpnext/dist/js/erpnext.bundle.XEIBO7ZF.js",
    "item-dashboard.bundle.js": "/assets/erpnext/dist/js/item-dashboard.bundle.NFSRRH7X.js",
    "point-of-sale.bundle.js": "/assets/erpnext/dist/js/point-of-sale.bundle.TLVBYXCL.js",
    "bom_configurator.bundle.js": "/assets/erpnext/dist/js/bom_configurator.bundle.OPXUQA72.js",
    "erpnext-web.bundle.css": "/assets/erpnext/dist/css/erpnext-web.bundle.CKSKVAPM.css",
    "erpnext.bundle.css": "/assets/erpnext/dist/css/erpnext.bundle.IXJCZ3CI.css",
    "erpnext_email.bundle.css": "/assets/erpnext/dist/css/erpnext_email.bundle.QK7YLRQ5.css"
}